mobio/libs/license/__init__.cpython-35m-darwin.so
mobio/libs/license/mobio_license_client.cpython-35m-darwin.so
m_license-1.9.dist-info/METADATA
m_license-1.9.dist-info/WHEEL
m_license-1.9.dist-info/top_level.txt
m_license-1.9.dist-info/RECORD
