Metadata-Version: 2.1
Name: m-license
Version: 1.9
Summary: Mobio libraries
Home-page: https://github.com/mobiovn
Author: MOBIO
Author-email: contact@mobio.vn
License: MOBIO
Platform: UNKNOWN
Requires-Dist: python-jose
Requires-Dist: pycryptodome (==3.4.3)
Requires-Dist: numpy
